arachnado/__init__.py
arachnado/__main__.py
arachnado/crawler_process.py
arachnado/handler_utils.py
arachnado/handlers.py
arachnado/manhole.py
arachnado/monitor.py
arachnado/options.py
arachnado/process_stats.py
arachnado/signals.py
arachnado/spider.py
arachnado/stats.py
arachnado/utils.py
arachnado/wsbase.py
arachnado/extensions/__init__.py
arachnado/extensions/httpcache.py
arachnado/extensions/throttle.py
arachnado/motor_exporter/__init__.py
arachnado/motor_exporter/pipelines.py
arachnado/motor_exporter/utils.py
arachnado/settings/defaults.conf
arachnado/static/build/common.js
arachnado/static/build/main.js
arachnado/static/build/vendor.js
arachnado/static/css/style.css
arachnado/static/js/common.js
arachnado/static/js/main.jsx
arachnado/static/js/components/ConnectionMonitor.jsx
arachnado/static/js/components/CrawlForm.jsx
arachnado/static/js/components/JobList.jsx
arachnado/static/js/components/JobStats.jsx
arachnado/static/js/components/JobTransfers.jsx
arachnado/static/js/components/KeyValueTable.jsx
arachnado/static/js/components/ProcessStats.jsx
arachnado/static/js/components/RefluxMixins.js
arachnado/static/js/pages/IndexPage.jsx
arachnado/static/js/pages/JobPage.jsx
arachnado/static/js/stores/ConnectionStore.js
arachnado/static/js/stores/JobStore.js
arachnado/static/js/stores/ProcessStatsStore.js
arachnado/static/js/utils/ArachnadoAPI.js
arachnado/static/js/utils/FancyWebSocket.js
arachnado/templates/base.html
arachnado/templates/help.html
arachnado/templates/index.html
arachnado-0.2.dist-info/DESCRIPTION.rst
arachnado-0.2.dist-info/entry_points.txt
arachnado-0.2.dist-info/METADATA
arachnado-0.2.dist-info/metadata.json
arachnado-0.2.dist-info/pbr.json
arachnado-0.2.dist-info/RECORD
arachnado-0.2.dist-info/top_level.txt
arachnado-0.2.dist-info/WHEEL
