Metadata-Version: 2.0
Name: arachnado
Version: 0.2
Summary: Scrapy-based Web Crawler with an UI
Home-page: https://github.com/TeamHG-Memex/arachnado
Author: Mikhail Korobov
Author-email: kmike84@gmail.com
License: MIT
Platform: UNKNOWN
Classifier: Framework :: Scrapy
Classifier: Development Status :: 3 - Alpha
Classifier: Intended Audience :: Developers
Classifier: License :: OSI Approved :: MIT License
Classifier: Operating System :: OS Independent
Classifier: Programming Language :: Python
Classifier: Programming Language :: Python :: 2
Classifier: Programming Language :: Python :: 2.7
Classifier: Topic :: Internet :: WWW/HTTP
Classifier: Topic :: Software Development :: Libraries :: Application Frameworks
Classifier: Topic :: Software Development :: Libraries :: Python Modules
Requires-Dist: scrapy (>=1.0.0)
Requires-Dist: Twisted (>=12)
Requires-Dist: psutil (>=2.2)
Requires-Dist: tornado (>=4.2)
Requires-Dist: docopt (>=0.6)
Requires-Dist: service-identity
